pwncat/__init__.py
pwncat/__main__.py
pwncat/channel/__init__.py
pwncat/channel/bind.py
pwncat/channel/connect.py
pwncat/channel/socket.py
pwncat/channel/ssh.py
pwncat/channel/ssl_bind.py
pwncat/channel/ssl_connect.py
pwncat/commands/__init__.py
pwncat/commands/alias.py
pwncat/commands/back.py
pwncat/commands/bind.py
pwncat/commands/connect.py
pwncat/commands/download.py
pwncat/commands/escalate.py
pwncat/commands/exit.py
pwncat/commands/help.py
pwncat/commands/info.py
pwncat/commands/lcd.py
pwncat/commands/leave.py
pwncat/commands/listener_new.py
pwncat/commands/listeners.py
pwncat/commands/load.py
pwncat/commands/local.py
pwncat/commands/lpwd.py
pwncat/commands/remember.py
pwncat/commands/reset.py
pwncat/commands/run.py
pwncat/commands/search.py
pwncat/commands/sessions.py
pwncat/commands/set.py
pwncat/commands/shortcut.py
pwncat/commands/upload.py
pwncat/commands/use.py
pwncat/config.py
pwncat/data/PowerSploit/.gitignore
pwncat/data/PowerSploit/AntivirusBypass/AntivirusBypass.psd1
pwncat/data/PowerSploit/AntivirusBypass/AntivirusBypass.psm1
pwncat/data/PowerSploit/AntivirusBypass/Find-AVSignature.ps1
pwncat/data/PowerSploit/AntivirusBypass/Usage.md
pwncat/data/PowerSploit/CodeExecution/CodeExecution.psd1
pwncat/data/PowerSploit/CodeExecution/CodeExecution.psm1
pwncat/data/PowerSploit/CodeExecution/Invoke-DllInjection.ps1
pwncat/data/PowerSploit/CodeExecution/Invoke-ReflectivePEInjection.ps1
pwncat/data/PowerSploit/CodeExecution/Invoke-ReflectivePEInjection_Resources/DemoDLL/DemoDLL/DemoDLL.cpp
pwncat/data/PowerSploit/CodeExecution/Invoke-ReflectivePEInjection_Resources/DemoDLL/DemoDLL/DemoDLL.h
pwncat/data/PowerSploit/CodeExecution/Invoke-ReflectivePEInjection_Resources/DemoDLL/DemoDLL/DemoDLL.vcxproj
pwncat/data/PowerSploit/CodeExecution/Invoke-ReflectivePEInjection_Resources/DemoDLL/DemoDLL/DemoDLL.vcxproj.filters
pwncat/data/PowerSploit/CodeExecution/Invoke-ReflectivePEInjection_Resources/DemoDLL/DemoDLL/ReadMe.txt
pwncat_vl-0.5.9.dist-info/LICENSE.md
pwncat_vl-0.5.9.dist-info/METADATA
pwncat_vl-0.5.9.dist-info/WHEEL
pwncat_vl-0.5.9.dist-info/entry_points.txt
pwncat_vl-0.5.9.dist-info/RECORD
