Metadata-Version: 2.3
Name: pwncat-vl
Version: 0.5.9
Summary: Community-maintained fork of pwncat with Python 3.13+ support
License: MIT
Keywords: offsec,cyber,exploitation,privesc,automation,redteam
Author: Chocapikk
Author-email: balgogan@protonmail.com
Requires-Python: >=3.9,<4.0
Classifier: License :: OSI Approved :: MIT License
Classifier: Programming Language :: Python :: 3
Classifier: Programming Language :: Python :: 3.9
Classifier: Programming Language :: Python :: 3.10
Classifier: Programming Language :: Python :: 3.11
Classifier: Programming Language :: Python :: 3.12
Classifier: Programming Language :: Python :: 3.13
Provides-Extra: docs
Requires-Dist: Jinja2 (>=3.0.1,<4.0.0)
Requires-Dist: PyNaCl (>=1.4.0,<2.0.0)
Requires-Dist: Sphinx (>=4.0.2,<5.0.0) ; extra == "docs"
Requires-Dist: ZODB3 (>=3.11.0,<4.0.0)
Requires-Dist: enum-tools (>=0.7.0,<0.8.0) ; extra == "docs"
Requires-Dist: furo (>=2021.11.23,<2022.0.0) ; extra == "docs"
Requires-Dist: netifaces (>=0.11.0,<0.12.0)
Requires-Dist: packaging (>=23.0)
Requires-Dist: paramiko-ng (>=2.8.8,<3.0.0)
Requires-Dist: passlib (>=1.7.4,<2.0.0)
Requires-Dist: prompt-toolkit (>=3.0.19,<4.0.0)
Requires-Dist: pycryptodome (>=3.10.1,<4.0.0)
Requires-Dist: python-rapidjson (>=1.0,<2.0)
Requires-Dist: requests (>=2.25.1,<3.0.0)
Requires-Dist: rich (>=10.4.0,<11.0.0)
Requires-Dist: sphinx-toolbox (>=2.15.2,<3.0.0) ; extra == "docs"
Requires-Dist: zodburi (>=2.5.0,<3.0.0)
Project-URL: Bug Tracker, https://github.com/Chocapikk/pwncat-vl/issues
Project-URL: Documentation, https://pwncat.readthedocs.io
Project-URL: Repository, https://github.com/Chocapikk/pwncat-vl
